glvis/__about__.py
glvis/__init__.py
glvis/util.py
glvis/widget.js
glvis/widget.py
glvis-1.1.1.dist-info/METADATA
glvis-1.1.1.dist-info/WHEEL
glvis-1.1.1.dist-info/licenses/LICENSE
glvis-1.1.1.dist-info/licenses/NOTICE
glvis-1.1.1.dist-info/RECORD
