Metadata-Version: 2.3
Name: glvis
Version: 1.1.1
Summary: GLVis widget for Jupyter notebooks
Project-URL: homepage, https://glvis.org
Project-URL: repostiory, https://github.com/glvis/pyglvis
License: BSD 3-Clause License
License-File: LICENSE
License-File: NOTICE
Requires-Dist: anywidget>=0.9.9
Requires-Dist: ipywidgets>=8.0.0
Requires-Dist: mfem>=4.5.2
